tfmplus/__init__.py
tfmplus/docs/How to install Benewake TF series on PixHawk.pdf
tfmplus/docs/TFmini Plus A05 Product Manual.pdf
tfmplus/docs/TFmini-Plus-01 A05_Datasheet.pdf
tfmplus/docs/__init__.py
tfmplus/tests/__init__.py
tfmplus/tests/tfmp_test.py
tfmplus-0.1.0.dist-info/LICENSE
tfmplus-0.1.0.dist-info/METADATA
tfmplus-0.1.0.dist-info/WHEEL
tfmplus-0.1.0.dist-info/top_level.txt
tfmplus-0.1.0.dist-info/RECORD
